lebai_sdk/__init__.py
lebai_sdk/__init__.pyi
lebai_sdk/lebai_sdk.pyd
lebai_sdk/py.typed
lebai_sdk_asyncio-0.3.5.dist-info/METADATA
lebai_sdk_asyncio-0.3.5.dist-info/WHEEL
lebai_sdk_asyncio-0.3.5.dist-info/licenses/LICENSE
lebai_sdk_asyncio-0.3.5.dist-info/RECORD
